BuildScour/__init__.py
BuildScour/__main__.py
BuildScour-1.0.4.dist-info/METADATA
BuildScour-1.0.4.dist-info/WHEEL
BuildScour-1.0.4.dist-info/top_level.txt
BuildScour-1.0.4.dist-info/RECORD
