Metadata-Version: 2.1
Name: BuildScour
Version: 1.0.4
Summary: Scours CI Build logs for github Organizations/Users
Home-page: https://github.com/darshkpatel/BuildScour
Author: Darsh Patel
Author-email: darshkpatel@gmail.com
License: MIT
Keywords: CI,RECONNAISSANCE,TRAVIS,LOGS,CIRCLE-CI
Platform: UNKNOWN
Classifier: Programming Language :: Python :: 3.6
Classifier: License :: OSI Approved :: MIT License
Classifier: Operating System :: Unix
Requires-Dist: argparse
Requires-Dist: requests
